nmn/__init__.py
nmn/keras/__init__.py
nmn/keras/conv.py
nmn/keras/nmn.py
nmn/linen/__init__.py
nmn/linen/conv.py
nmn/linen/nmn.py
nmn/nnx/conv_utils.py
nmn/nnx/nmn.py
nmn/nnx/yatattention.py
nmn/nnx/yatconv.py
nmn/nnx/yatconv_transpose.py
nmn/nnx/attention/__init__.py
nmn/nnx/attention/dot_product.py
nmn/nnx/attention/masks.py
nmn/nnx/attention/multi_head.py
nmn/nnx/attention/rotary_yat.py
nmn/nnx/attention/spherical_yat_performer.py
nmn/nnx/attention/yat_attention.py
nmn/nnx/conv/__init__.py
nmn/nnx/conv/utils.py
nmn/nnx/conv/yat_conv.py
nmn/nnx/conv/yat_conv_transpose.py
nmn/nnx/examples/language/m3za.py
nmn/nnx/examples/language/m3za_perf.py
nmn/nnx/examples/language/mingpt.py
nmn/nnx/examples/vision/cnn_cifar.py
nmn/nnx/loss/__init__.py
nmn/nnx/rnn/DISCLAIMER.md
nmn/nnx/rnn/__init__.py
nmn/nnx/rnn/gru.py
nmn/nnx/rnn/lstm.py
nmn/nnx/rnn/rnn_utils.py
nmn/nnx/rnn/simple.py
nmn/nnx/squashers/__init__.py
nmn/nnx/squashers/soft_tanh.py
nmn/nnx/squashers/softer_sigmoid.py
nmn/nnx/squashers/softermax.py
nmn/tf/__init__.py
nmn/tf/conv.py
nmn/tf/nmn.py
nmn/torch/__init__.py
nmn/torch/base.py
nmn/torch/examples/README.md
nmn/torch/examples/yat_cifar10.py
nmn/torch/examples/yat_examples.py
nmn/torch/examples/vision/resnet_training.py
nmn/torch/layers/__init__.py
nmn/torch/layers/yat_conv1d.py
nmn/torch/layers/yat_conv2d.py
nmn/torch/layers/yat_conv3d.py
nmn/torch/layers/yat_conv_transpose1d.py
nmn/torch/layers/yat_conv_transpose2d.py
nmn/torch/layers/yat_conv_transpose3d.py
nmn/torch/nmn/__init__.py
nmn/torch/nmn/yat_nmn.py
nmn-0.2.6.dist-info/METADATA
nmn-0.2.6.dist-info/WHEEL
nmn-0.2.6.dist-info/licenses/LICENSE
nmn-0.2.6.dist-info/RECORD
