Metadata-Version: 2.4
Name: nmn
Version: 0.2.6
Summary: Neural-Matter Network (NMN) - Advanced neural network layers with attention mechanisms
Project-URL: Homepage, https://github.com/mlnomadpy/nmn
Project-URL: Bug Tracker, https://github.com/mlnomadpy/nmn/issues
Author-email: Taha Bouhsine <taha@azetta.ai>
License-File: LICENSE
Classifier: License :: OSI Approved :: GNU Affero General Public License v3
Classifier: Operating System :: OS Independent
Classifier: Programming Language :: Python :: 3
Requires-Python: >=3.8
Provides-Extra: all
Requires-Dist: flax>=0.7.0; extra == 'all'
Requires-Dist: jax>=0.4.0; extra == 'all'
Requires-Dist: tensorflow>=2.10.0; extra == 'all'
Requires-Dist: torch>=1.11.0; extra == 'all'
Requires-Dist: torchvision>=0.12.0; extra == 'all'
Provides-Extra: dev
Requires-Dist: black>=23.0.0; extra == 'dev'
Requires-Dist: flake8>=6.0.0; extra == 'dev'
Requires-Dist: isort>=5.12.0; extra == 'dev'
Requires-Dist: mypy>=1.0.0; extra == 'dev'
Requires-Dist: pytest-cov>=4.0.0; extra == 'dev'
Requires-Dist: pytest>=7.0.0; extra == 'dev'
Provides-Extra: keras
Requires-Dist: tensorflow>=2.10.0; extra == 'keras'
Provides-Extra: linen
Requires-Dist: flax>=0.7.0; extra == 'linen'
Requires-Dist: jax>=0.4.0; extra == 'linen'
Provides-Extra: nnx
Requires-Dist: flax>=0.7.0; extra == 'nnx'
Requires-Dist: jax>=0.4.0; extra == 'nnx'
Provides-Extra: test
Requires-Dist: black>=23.0.0; extra == 'test'
Requires-Dist: flake8>=6.0.0; extra == 'test'
Requires-Dist: flax>=0.7.0; extra == 'test'
Requires-Dist: isort>=5.12.0; extra == 'test'
Requires-Dist: jax>=0.4.0; extra == 'test'
Requires-Dist: matplotlib>=3.5.0; extra == 'test'
Requires-Dist: mypy>=1.0.0; extra == 'test'
Requires-Dist: optax>=0.1.4; extra == 'test'
Requires-Dist: pytest-cov>=4.0.0; extra == 'test'
Requires-Dist: pytest>=7.0.0; extra == 'test'
Requires-Dist: scikit-learn>=1.1.0; extra == 'test'
Requires-Dist: seaborn>=0.11.0; extra == 'test'
Requires-Dist: tensorflow-datasets>=4.8.0; extra == 'test'
Requires-Dist: tensorflow>=2.10.0; extra == 'test'
Requires-Dist: torch>=1.11.0; extra == 'test'
Requires-Dist: torchvision>=0.12.0; extra == 'test'
Provides-Extra: tf
Requires-Dist: tensorflow>=2.10.0; extra == 'tf'
Provides-Extra: torch
Requires-Dist: torch>=1.11.0; extra == 'torch'
Requires-Dist: torchvision>=0.12.0; extra == 'torch'
